dialsim/#TODO list.md
dialsim/__init__.py
dialsim/agent.py
dialsim/simulator.py
dialsim/logging_results/__init__.py
dialsim/logging_results/logging.py
dialsim/models/__init__.py
dialsim/models/api_based_inference.py
dialsim/models/load_gemini.py
dialsim/models/load_model.py
dialsim/models/load_opensource_model.py
dialsim/models/open_source_model_inference.py
dialsim/post_processing/__init__.py
dialsim/post_processing/process_answer.py
dialsim/prompt/RAG_qa_prompt.txt
dialsim/prompt/RAG_qa_prompt_multi_choice_structured.txt
dialsim/prompt/RAG_qa_prompt_multi_choice_unstructured.txt
dialsim/prompt/RAG_qa_prompt_open_ended.txt
dialsim/prompt/chatgpt_summarize_prompt.txt
dialsim/prompt/naive_llm_inference.txt
dialsim/prompt/naive_llm_inference_multi_choice_structured.txt
dialsim/prompt/naive_llm_inference_multi_choice_unstructured.txt
dialsim/prompt/naive_llm_inference_open_ended.txt
dialsim/prompt/openie_utt_prompt.txt
dialsim/utils/__init__.py
dialsim/utils/utils.py
dialsim-0.0.36.dist-info/METADATA
dialsim-0.0.36.dist-info/WHEEL
dialsim-0.0.36.dist-info/licenses/LICENSE
dialsim-0.0.36.dist-info/RECORD
