Metadata-Version: 2.3
Name: DialSim
Version: 0.0.36
Summary: DialSim package
Project-URL: Homepage, https://dialsim.github.io/
Project-URL: Bug Tracker, https://github.com/jiho283/Simulator/issues
Author-email: Jiho Kim <jiho.kim@kaist.ac.kr>, Woosog Chay <benchay@kaist.ac.kr>
License: MIT License
License-File: LICENSE
Keywords: conversational agents,evaluation,natural language processing,simulator
Classifier: License :: OSI Approved :: MIT License
Classifier: Operating System :: OS Independent
Classifier: Programming Language :: Python :: 3
Requires-Python: <3.12,>=3.9
Requires-Dist: accelerate
Requires-Dist: anthropic
Requires-Dist: bitsandbytes
Requires-Dist: func-timeout
Requires-Dist: google-generativeai
Requires-Dist: huggingface-hub
Requires-Dist: nltk
Requires-Dist: numpy
Requires-Dist: openai
Requires-Dist: pandas
Requires-Dist: rank-bm25
Requires-Dist: scikit-learn
Requires-Dist: sentencepiece
Requires-Dist: toml
Requires-Dist: torch
Requires-Dist: transformers
Requires-Dist: types-toml
